{"@context":"https://iiif.io/api/presentation/3/context.json","id":"https://mathewjordan.github.io/iiif-conference-2025-canopy/api/facet/dimensions/6-cm-height-x-6-cm-width.json","type":"Collection","label":{"none":["6 cm (height) x 6 cm (width)"]},"items":[{"id":"https://api.dc.library.northwestern.edu/api/v2/works/3657c26f-030e-4ef2-b51a-3e72f3ebf2a1?as=iiif","type":"Manifest","label":{"none":["Bird cage"]},"thumbnail":[{"id":"https://api.dc.library.northwestern.edu/api/v2/works/3657c26f-030e-4ef2-b51a-3e72f3ebf2a1/thumbnail","type":"Image","format":"image/jpeg","height":300,"width":300}],"homepage":[{"id":"https://mathewjordan.github.io/iiif-conference-2025-canopy/works/bird-cage","type":"Text","label":{"none":["Bird cage"]}}]}],"partOf":[{"id":"https://mathewjordan.github.io/iiif-conference-2025-canopy/api/facet/dimensions.json","type":"Collection"}],"summary":{"none":["Dimensions"]},"homepage":[{"id":"https://mathewjordan.github.io/iiif-conference-2025-canopy/search?dimensions=6-cm-height-x-6-cm-width","type":"Text","label":{"none":["6 cm (height) x 6 cm (width)"]}}]}